reimport.py
setup.cfg
setup.py
reimport.egg-info/PKG-INFO
reimport.egg-info/SOURCES.txt
reimport.egg-info/dependency_links.txt
reimport.egg-info/top_level.txt
reimport.egg-info/zip-safe